[
  {"id":"user_1773052819521","userId":"1000001","email":"admin@matrixmlm.com","password":"admin123","fullName":"System Administrator","phone":"+1234567890","country":"USA","isActive":true,"isAdmin":true,"accountStatus":"active","blockedAt":null,"blockedUntil":null,"blockedReason":null,"createdAt":"2026-03-09T10:40:19.521Z","activatedAt":"2026-03-09T10:40:19.521Z","gracePeriodEnd":null,"sponsorId":null,"parentId":null,"position":null,"level":0,"directCount":100,"totalEarnings":0,"isCapped":false,"capLevel":0,"reEntryCount":0,"cycleCount":0,"requiredDirectForNextLevel":0,"completedDirectForCurrentLevel":0,"transactionPassword":"trans123","emailVerified":true,"achievements":{"nationalTour":false,"internationalTour":false,"familyTour":false}},
  {"id":"user_1773052961477_0","userId":"3969959","email":"admin.bulk.1000001.1773052961477.0@auto.local","password":"user123","fullName":"Member 001","phone":"2961477035","country":"India","isActive":true,"isAdmin":false,"accountStatus":"active","blockedAt":null,"blockedUntil":null,"blockedReason":null,"createdAt":"2026-03-09T10:42:41.477Z","activatedAt":"2026-03-09T10:42:41.477Z","gracePeriodEnd":null,"sponsorId":"1000001","parentId":"1000001","position":"left","level":0,"directCount":0,"totalEarnings":0,"isCapped":false,"capLevel":0,"reEntryCount":0,"cycleCount":0,"requiredDirectForNextLevel":2,"completedDirectForCurrentLevel":0,"transactionPassword":"1234","emailVerified":false,"achievements":{"nationalTour":false,"internationalTour":false,"familyTour":false}},
  {"id":"user_1773052961478_1","userId":"2245509","email":"admin.bulk.1000001.1773052961477.1@auto.local","password":"user123","fullName":"Member 002","phone":"9614781412","country":"India","isActive":true,"isAdmin":false,"accountStatus":"active","blockedAt":null,"blockedUntil":null,"blockedReason":null,"createdAt":"2026-03-09T10:42:41.478Z","activatedAt":"2026-03-09T10:42:41.478Z","gracePeriodEnd":null,"sponsorId":"1000001","parentId":"1000001","position":"right","level":0,"directCount":0,"totalEarnings":0,"isCapped":false,"capLevel":0,"reEntryCount":0,"cycleCount":0,"requiredDirectForNextLevel":2,"completedDirectForCurrentLevel":0,"transactionPassword":"1234","emailVerified":false,"achievements":{"nationalTour":false,"internationalTour":false,"familyTour":false}},
  {"id":"user_1773052961479_2","userId":"8955962","email":"admin.bulk.1000001.1773052961477.2@auto.local","password":"user123","fullName":"Member 003","phone":"9614792870","country":"India","isActive":true,"isAdmin":false,"accountStatus":"active","blockedAt":null,"blockedUntil":null,"blockedReason":null,"createdAt":"2026-03-09T10:42:41.479Z","activatedAt":"2026-03-09T10:42:41.479Z","gracePeriodEnd":null,"sponsorId":"1000001","parentId":"3969959","position":"left","level":0,"directCount":0,"totalEarnings":0,"isCapped":false,"capLevel":0,"reEntryCount":0,"cycleCount":0,"requiredDirectForNextLevel":2,"completedDirectForCurrentLevel":0,"transactionPassword":"1234","emailVerified":false,"achievements":{"nationalTour":false,"internationalTour":false,"familyTour":false}},
  {"id":"user_1773052961480_3","userId":"5019444","email":"admin.bulk.1000001.1773052961477.3@auto.local","password":"user123","fullName":"Member 004","phone":"9614803937","country":"India","isActive":true,"isAdmin":false,"accountStatus":"active","blockedAt":null,"blockedUntil":null,"blockedReason":null,"createdAt":"2026-03-09T10:42:41.480Z","activatedAt":"2026-03-09T10:42:41.480Z","gracePeriodEnd":null,"sponsorId":"1000001","parentId":"3969959","position":"right","level":0,"directCount":0,"totalEarnings":0,"isCapped":false,"capLevel":0,"reEntryCount":0,"cycleCount":0,"requiredDirectForNextLevel":2,"completedDirectForCurrentLevel":0,"transactionPassword":"1234","emailVerified":false,"achievements":{"nationalTour":false,"internationalTour":false,"familyTour":false}},
  {"id":"user_1773052961480_4","userId":"7591566","email":"admin.bulk.1000001.1773052961477.4@auto.local","password":"user123","fullName":"Member 005","phone":"2961480437","country":"India","isActive":true,"isAdmin":false,"accountStatus":"active","blockedAt":null,"blockedUntil":null,"blockedReason":null,"createdAt":"2026-03-09T10:42:41.480Z","activatedAt":"2026-03-09T10:42:41.480Z","gracePeriodEnd":null,"sponsorId":"1000001","parentId":"2245509","position":"left","level":0,"directCount":0,"totalEarnings":0,"isCapped":false,"capLevel":0,"reEntryCount":0,"cycleCount":0,"requiredDirectForNextLevel":2,"completedDirectForCurrentLevel":0,"transactionPassword":"1234","emailVerified":false,"achievements":{"nationalTour":false,"internationalTour":false,"familyTour":false}},
  {"id":"user_1773052961481_5","userId":"6674013","email":"admin.bulk.1000001.1773052961477.5@auto.local","password":"user123","fullName":"Member 006","phone":"9614815739","country":"India","isActive":true,"isAdmin":false,"accountStatus":"active","blockedAt":null,"blockedUntil":null,"blockedReason":null,"createdAt":"2026-03-09T10:42:41.481Z","activatedAt":"2026-03-09T10:42:41.481Z","gracePeriodEnd":null,"sponsorId":"1000001","parentId":"2245509","position":"right","level":0,"directCount":0,"totalEarnings":0,"isCapped":false,"capLevel":0,"reEntryCount":0,"cycleCount":0,"requiredDirectForNextLevel":2,"completedDirectForCurrentLevel":0,"transactionPassword":"1234","emailVerified":false,"achievements":{"nationalTour":false,"internationalTour":false,"familyTour":false}},
  {"id":"user_1773052961481_6","userId":"9996798","email":"admin.bulk.1000001.1773052961477.6@auto.local","password":"user123","fullName":"Member 007","phone":"9614816546","country":"India","isActive":true,"isAdmin":false,"accountStatus":"active","blockedAt":null,"blockedUntil":null,"blockedReason":null,"createdAt":"2026-03-09T10:42:41.481Z","activatedAt":"2026-03-09T10:42:41.481Z","gracePeriodEnd":null,"sponsorId":"1000001","parentId":"8955962","position":"left","level":0,"directCount":0,"totalEarnings":0,"isCapped":false,"capLevel":0,"reEntryCount":0,"cycleCount":0,"requiredDirectForNextLevel":2,"completedDirectForCurrentLevel":0,"transactionPassword":"1234","emailVerified":false,"achievements":{"nationalTour":false,"internationalTour":false,"familyTour":false}},
  {"id":"user_1773052961482_7","userId":"4434570","email":"admin.bulk.1000001.1773052961477.7@auto.local","password":"user123","fullName":"Member 008","phone":"5296148273","country":"India","isActive":true,"isAdmin":false,"accountStatus":"active","blockedAt":null,"blockedUntil":null,"blockedReason":null,"createdAt":"2026-03-09T10:42:41.482Z","activatedAt":"2026-03-09T10:42:41.482Z","gracePeriodEnd":null,"sponsorId":"1000001","parentId":"8955962","position":"right","level":0,"directCount":0,"totalEarnings":0,"isCapped":false,"capLevel":0,"reEntryCount":0,"cycleCount":0,"requiredDirectForNextLevel":2,"completedDirectForCurrentLevel":0,"transactionPassword":"1234","emailVerified":false,"achievements":{"nationalTour":false,"internationalTour":false,"familyTour":false}},
  {"id":"user_1773052961483_8","userId":"8861569","email":"admin.bulk.1000001.1773052961477.8@auto.local","password":"user123","fullName":"Member 009","phone":"9614838315","country":"India","isActive":true,"isAdmin":false,"accountStatus":"active","blockedAt":null,"blockedUntil":null,"blockedReason":null,"createdAt":"2026-03-09T10:42:41.483Z","activatedAt":"2026-03-09T10:42:41.483Z","gracePeriodEnd":null,"sponsorId":"1000001","parentId":"5019444","position":"left","level":0,"directCount":0,"totalEarnings":0,"isCapped":false,"capLevel":0,"reEntryCount":0,"cycleCount":0,"requiredDirectForNextLevel":2,"completedDirectForCurrentLevel":0,"transactionPassword":"1234","emailVerified":false,"achievements":{"nationalTour":false,"internationalTour":false,"familyTour":false}},
  {"id":"user_1773052961483_9","userId":"3139128","email":"admin.bulk.1000001.1773052961477.9@auto.local","password":"user123","fullName":"Member 010","phone":"9614839429","country":"India","isActive":true,"isAdmin":false,"accountStatus":"active","blockedAt":null,"blockedUntil":null,"blockedReason":null,"createdAt":"2026-03-09T10:42:41.483Z","activatedAt":"2026-03-09T10:42:41.483Z","gracePeriodEnd":null,"sponsorId":"1000001","parentId":"5019444","position":"right","level":0,"directCount":0,"totalEarnings":0,"isCapped":false,"capLevel":0,"reEntryCount":0,"cycleCount":0,"requiredDirectForNextLevel":2,"completedDirectForCurrentLevel":0,"transactionPassword":"1234","emailVerified":false,"achievements":{"nationalTour":false,"internationalTour":false,"familyTour":false}},
  {"id":"user_1773052961702_10","userId":"1736670","email":"admin.bulk.1000001.1773052961477.10@auto.local","password":"user123","fullName":"Member 011","phone":"6170210562","country":"India","isActive":true,"isAdmin":false,"accountStatus":"active","blockedAt":null,"blockedUntil":null,"blockedReason":null,"createdAt":"2026-03-09T10:42:41.702Z","activatedAt":"2026-03-09T10:42:41.702Z","gracePeriodEnd":null,"sponsorId":"1000001","parentId":"7591566","position":"left","level":0,"directCount":0,"totalEarnings":0,"isCapped":false,"capLevel":0,"reEntryCount":0,"cycleCount":0,"requiredDirectForNextLevel":2,"completedDirectForCurrentLevel":0,"transactionPassword":"1234","emailVerified":false,"achievements":{"nationalTour":false,"internationalTour":false,"familyTour":false}},
  {"id":"user_1773052961702_11","userId":"1144227","email":"admin.bulk.1000001.1773052961477.11@auto.local","password":"user123","fullName":"Member 012","phone":"6170211702","country":"India","isActive":true,"isAdmin":false,"accountStatus":"active","blockedAt":null,"blockedUntil":null,"blockedReason":null,"createdAt":"2026-03-09T10:42:41.702Z","activatedAt":"2026-03-09T10:42:41.702Z","gracePeriodEnd":null,"sponsorId":"1000001","parentId":"7591566","position":"right","level":0,"directCount":0,"totalEarnings":0,"isCapped":false,"capLevel":0,"reEntryCount":0,"cycleCount":0,"requiredDirectForNextLevel":2,"completedDirectForCurrentLevel":0,"transactionPassword":"1234","emailVerified":false,"achievements":{"nationalTour":false,"internationalTour":false,"familyTour":false}},
  {"id":"user_1773052961703_12","userId":"6996642","email":"admin.bulk.1000001.1773052961477.12@auto.local","password":"user123","fullName":"Member 013","phone":"6170312365","country":"India","isActive":true,"isAdmin":false,"accountStatus":"active","blockedAt":null,"blockedUntil":null,"blockedReason":null,"createdAt":"2026-03-09T10:42:41.703Z","activatedAt":"2026-03-09T10:42:41.703Z","gracePeriodEnd":null,"sponsorId":"1000001","parentId":"6674013","position":"left","level":0,"directCount":0,"totalEarnings":0,"isCapped":false,"capLevel":0,"reEntryCount":0,"cycleCount":0,"requiredDirectForNextLevel":2,"completedDirectForCurrentLevel":0,"transactionPassword":"1234","emailVerified":false,"achievements":{"nationalTour":false,"internationalTour":false,"familyTour":false}},
  {"id":"user_1773052961703_13","userId":"6369838","email":"admin.bulk.1000001.1773052961477.13@auto.local","password":"user123","fullName":"Member 014","phone":"6170313375","country":"India","isActive":true,"isAdmin":false,"accountStatus":"active","blockedAt":null,"blockedUntil":null,"blockedReason":null,"createdAt":"2026-03-09T10:42:41.703Z","activatedAt":"2026-03-09T10:42:41.703Z","gracePeriodEnd":null,"sponsorId":"1000001","parentId":"6674013","position":"right","level":0,"directCount":0,"totalEarnings":0,"isCapped":false,"capLevel":0,"reEntryCount":0,"cycleCount":0,"requiredDirectForNextLevel":2,"completedDirectForCurrentLevel":0,"transactionPassword":"1234","emailVerified":false,"achievements":{"nationalTour":false,"internationalTour":false,"familyTour":false}},
  {"id":"user_1773052961704_14","userId":"4941364","email":"admin.bulk.1000001.1773052961477.14@auto.local","password":"user123","fullName":"Member 015","phone":"6170414444","country":"India","isActive":true,"isAdmin":false,"accountStatus":"active","blockedAt":null,"blockedUntil":null,"blockedReason":null,"createdAt":"2026-03-09T10:42:41.704Z","activatedAt":"2026-03-09T10:42:41.704Z","gracePeriodEnd":null,"sponsorId":"1000001","parentId":"9996798","position":"left","level":0,"directCount":0,"totalEarnings":0,"isCapped":false,"capLevel":0,"reEntryCount":0,"cycleCount":0,"requiredDirectForNextLevel":2,"completedDirectForCurrentLevel":0,"transactionPassword":"1234","emailVerified":false,"achievements":{"nationalTour":false,"internationalTour":false,"familyTour":false}},
  {"id":"user_1773052961705_15","userId":"3535377","email":"admin.bulk.1000001.1773052961477.15@auto.local","password":"user123","fullName":"Member 016","phone":"6170515218","country":"India","isActive":true,"isAdmin":false,"accountStatus":"active","blockedAt":null,"blockedUntil":null,"blockedReason":null,"createdAt":"2026-03-09T10:42:41.705Z","activatedAt":"2026-03-09T10:42:41.705Z","gracePeriodEnd":null,"sponsorId":"1000001","parentId":"9996798","position":"right","level":0,"directCount":0,"totalEarnings":0,"isCapped":false,"capLevel":0,"reEntryCount":0,"cycleCount":0,"requiredDirectForNextLevel":2,"completedDirectForCurrentLevel":0,"transactionPassword":"1234","emailVerified":false,"achievements":{"nationalTour":false,"internationalTour":false,"familyTour":false}},
  {"id":"user_1773052961706_16","userId":"3315481","email":"admin.bulk.1000001.1773052961477.16@auto.local","password":"user123","fullName":"Member 017","phone":"6170616907","country":"India","isActive":true,"isAdmin":false,"accountStatus":"active","blockedAt":null,"blockedUntil":null,"blockedReason":null,"createdAt":"2026-03-09T10:42:41.706Z","activatedAt":"2026-03-09T10:42:41.706Z","gracePeriodEnd":null,"sponsorId":"1000001","parentId":"4434570","position":"left","level":0,"directCount":0,"totalEarnings":0,"isCapped":false,"capLevel":0,"reEntryCount":0,"cycleCount":0,"requiredDirectForNextLevel":2,"completedDirectForCurrentLevel":0,"transactionPassword":"1234","emailVerified":false,"achievements":{"nationalTour":false,"internationalTour":false,"familyTour":false}},
  {"id":"user_1773052961707_17","userId":"9891686","email":"admin.bulk.1000001.1773052961477.17@auto.local","password":"user123","fullName":"Member 018","phone":"6170717357","country":"India","isActive":true,"isAdmin":false,"accountStatus":"active","blockedAt":null,"blockedUntil":null,"blockedReason":null,"createdAt":"2026-03-09T10:42:41.707Z","activatedAt":"2026-03-09T10:42:41.707Z","gracePeriodEnd":null,"sponsorId":"1000001","parentId":"4434570","position":"right","level":0,"directCount":0,"totalEarnings":0,"isCapped":false,"capLevel":0,"reEntryCount":0,"cycleCount":0,"requiredDirectForNextLevel":2,"completedDirectForCurrentLevel":0,"transactionPassword":"1234","emailVerified":false,"achievements":{"nationalTour":false,"internationalTour":false,"familyTour":false}},
  {"id":"user_1773052961708_18","userId":"2901818","email":"admin.bulk.1000001.1773052961477.18@auto.local","password":"user123","fullName":"Member 019","phone":"2961708188","country":"India","isActive":true,"isAdmin":false,"accountStatus":"active","blockedAt":null,"blockedUntil":null,"blockedReason":null,"createdAt":"2026-03-09T10:42:41.708Z","activatedAt":"2026-03-09T10:42:41.708Z","gracePeriodEnd":null,"sponsorId":"1000001","parentId":"8861569","position":"left","level":0,"directCount":0,"totalEarnings":0,"isCapped":false,"capLevel":0,"reEntryCount":0,"cycleCount":0,"requiredDirectForNextLevel":2,"completedDirectForCurrentLevel":0,"transactionPassword":"1234","emailVerified":false,"achievements":{"nationalTour":false,"internationalTour":false,"familyTour":false}},
  {"id":"user_1773052961709_19","userId":"4173921","email":"admin.bulk.1000001.1773052961477.19@auto.local","password":"user123","fullName":"Member 020","phone":"6170919436","country":"India","isActive":true,"isAdmin":false,"accountStatus":"active","blockedAt":null,"blockedUntil":null,"blockedReason":null,"createdAt":"2026-03-09T10:42:41.709Z","activatedAt":"2026-03-09T10:42:41.709Z","gracePeriodEnd":null,"sponsorId":"1000001","parentId":"8861569","position":"right","level":0,"directCount":0,"totalEarnings":0,"isCapped":false,"capLevel":0,"reEntryCount":0,"cycleCount":0,"requiredDirectForNextLevel":2,"completedDirectForCurrentLevel":0,"transactionPassword":"1234","emailVerified":false,"achievements":{"nationalTour":false,"internationalTour":false,"familyTour":false}},
  {"id":"user_1773052961937_20","userId":"4130042","email":"admin.bulk.1000001.1773052961477.20@auto.local","password":"user123","fullName":"Member 021","phone":"6193720873","country":"India","isActive":true,"isAdmin":false,"accountStatus":"active","blockedAt":null,"blockedUntil":null,"blockedReason":null,"createdAt":"2026-03-09T10:42:41.937Z","activatedAt":"2026-03-09T10:42:41.937Z","gracePeriodEnd":null,"sponsorId":"1000001","parentId":"3139128","position":"left","level":0,"directCount":0,"totalEarnings":0,"isCapped":false,"capLevel":0,"reEntryCount":0,"cycleCount":0,"requiredDirectForNextLevel":2,"completedDirectForCurrentLevel":0,"transactionPassword":"1234","emailVerified":false,"achievements":{"nationalTour":false,"internationalTour":false,"familyTour":false}},
  {"id":"user_1773052961938_21","userId":"9671746","email":"admin.bulk.1000001.1773052961477.21@auto.local","password":"user123","fullName":"Member 022","phone":"6193821652","country":"India","isActive":true,"isAdmin":false,"accountStatus":"active","blockedAt":null,"blockedUntil":null,"blockedReason":null,"createdAt":"2026-03-09T10:42:41.938Z","activatedAt":"2026-03-09T10:42:41.938Z","gracePeriodEnd":null,"sponsorId":"1000001","parentId":"3139128","position":"right","level":0,"directCount":0,"totalEarnings":0,"isCapped":false,"capLevel":0,"reEntryCount":0,"cycleCount":0,"requiredDirectForNextLevel":2,"completedDirectForCurrentLevel":0,"transactionPassword":"1234","emailVerified":false,"achievements":{"nationalTour":false,"internationalTour":false,"familyTour":false}},
  {"id":"user_1773052961939_22","userId":"5148139","email":"admin.bulk.1000001.1773052961477.22@auto.local","password":"user123","fullName":"Member 023","phone":"6193922445","country":"India","isActive":true,"isAdmin":false,"accountStatus":"active","blockedAt":null,"blockedUntil":null,"blockedReason":null,"createdAt":"2026-03-09T10:42:41.939Z","activatedAt":"2026-03-09T10:42:41.939Z","gracePeriodEnd":null,"sponsorId":"1000001","parentId":"1736670","position":"left","level":0,"directCount":0,"totalEarnings":0,"isCapped":false,"capLevel":0,"reEntryCount":0,"cycleCount":0,"requiredDirectForNextLevel":2,"completedDirectForCurrentLevel":0,"transactionPassword":"1234","emailVerified":false,"achievements":{"nationalTour":false,"internationalTour":false,"familyTour":false}},
  {"id":"user_1773052961940_23","userId":"5488566","email":"admin.bulk.1000001.1773052961477.23@auto.local","password":"user123","fullName":"Member 024","phone":"9619402397","country":"India","isActive":true,"isAdmin":false,"accountStatus":"active","blockedAt":null,"blockedUntil":null,"blockedReason":null,"createdAt":"2026-03-09T10:42:41.940Z","activatedAt":"2026-03-09T10:42:41.940Z","gracePeriodEnd":null,"sponsorId":"1000001","parentId":"1736670","position":"right","level":0,"directCount":0,"totalEarnings":0,"isCapped":false,"capLevel":0,"reEntryCount":0,"cycleCount":0,"requiredDirectForNextLevel":2,"completedDirectForCurrentLevel":0,"transactionPassword":"1234","emailVerified":false,"achievements":{"nationalTour":false,"internationalTour":false,"familyTour":false}},
  {"id":"user_1773052961940_24","userId":"2782991","email":"admin.bulk.1000001.1773052961477.24@auto.local","password":"user123","fullName":"Member 025","phone":"6194024583","country":"India","isActive":true,"isAdmin":false,"accountStatus":"active","blockedAt":null,"blockedUntil":null,"blockedReason":null,"createdAt":"2026-03-09T10:42:41.940Z","activatedAt":"2026-03-09T10:42:41.940Z","gracePeriodEnd":null,"sponsorId":"1000001","parentId":"1144227","position":"left","level":0,"directCount":0,"totalEarnings":0,"isCapped":false,"capLevel":0,"reEntryCount":0,"cycleCount":0,"requiredDirectForNextLevel":2,"completedDirectForCurrentLevel":0,"transactionPassword":"1234","emailVerified":false,"achievements":{"nationalTour":false,"internationalTour":false,"familyTour":false}},
  {"id":"user_1773052961941_25","userId":"1442967","email":"admin.bulk.1000001.1773052961477.25@auto.local","password":"user123","fullName":"Member 026","phone":"6194125646","country":"India","isActive":true,"isAdmin":false,"accountStatus":"active","blockedAt":null,"blockedUntil":null,"blockedReason":null,"createdAt":"2026-03-09T10:42:41.941Z","activatedAt":"2026-03-09T10:42:41.941Z","gracePeriodEnd":null,"sponsorId":"1000001","parentId":"1144227","position":"right","level":0,"directCount":0,"totalEarnings":0,"isCapped":false,"capLevel":0,"reEntryCount":0,"cycleCount":0,"requiredDirectForNextLevel":2,"completedDirectForCurrentLevel":0,"transactionPassword":"1234","emailVerified":false,"achievements":{"nationalTour":false,"internationalTour":false,"familyTour":false}},
  {"id":"user_1773052961941_26","userId":"5565441","email":"admin.bulk.1000001.1773052961477.26@auto.local","password":"user123","fullName":"Member 027","phone":"9619412673","country":"India","isActive":true,"isAdmin":false,"accountStatus":"active","blockedAt":null,"blockedUntil":null,"blockedReason":null,"createdAt":"2026-03-09T10:42:41.941Z","activatedAt":"2026-03-09T10:42:41.941Z","gracePeriodEnd":null,"sponsorId":"1000001","parentId":"6996642","position":"left","level":0,"directCount":0,"totalEarnings":0,"isCapped":false,"capLevel":0,"reEntryCount":0,"cycleCount":0,"requiredDirectForNextLevel":2,"completedDirectForCurrentLevel":0,"transactionPassword":"1234","emailVerified":false,"achievements":{"nationalTour":false,"internationalTour":false,"familyTour":false}},
  {"id":"user_1773052961942_27","userId":"7959608","email":"admin.bulk.1000001.1773052961477.27@auto.local","password":"user123","fullName":"Member 028","phone":"6194227607","country":"India","isActive":true,"isAdmin":false,"accountStatus":"active","blockedAt":null,"blockedUntil":null,"blockedReason":null,"createdAt":"2026-03-09T10:42:41.942Z","activatedAt":"2026-03-09T10:42:41.942Z","gracePeriodEnd":null,"sponsorId":"1000001","parentId":"6996642","position":"right","level":0,"directCount":0,"totalEarnings":0,"isCapped":false,"capLevel":0,"reEntryCount":0,"cycleCount":0,"requiredDirectForNextLevel":2,"completedDirectForCurrentLevel":0,"transactionPassword":"1234","emailVerified":false,"achievements":{"nationalTour":false,"internationalTour":false,"familyTour":false}},
  {"id":"user_1773052961942_28","userId":"6184215","email":"admin.bulk.1000001.1773052961477.28@auto.local","password":"user123","fullName":"Member 029","phone":"6194228346","country":"India","isActive":true,"isAdmin":false,"accountStatus":"active","blockedAt":null,"blockedUntil":null,"blockedReason":null,"createdAt":"2026-03-09T10:42:41.942Z","activatedAt":"2026-03-09T10:42:41.942Z","gracePeriodEnd":null,"sponsorId":"1000001","parentId":"6369838","position":"left","level":0,"directCount":0,"totalEarnings":0,"isCapped":false,"capLevel":0,"reEntryCount":0,"cycleCount":0,"requiredDirectForNextLevel":2,"completedDirectForCurrentLevel":0,"transactionPassword":"1234","emailVerified":false,"achievements":{"nationalTour":false,"internationalTour":false,"familyTour":false}},
  {"id":"user_1773052961943_29","userId":"3251493","email":"admin.bulk.1000001.1773052961477.29@auto.local","password":"user123","fullName":"Member 030","phone":"6194329964","country":"India","isActive":true,"isAdmin":false,"accountStatus":"active","blockedAt":null,"blockedUntil":null,"blockedReason":null,"createdAt":"2026-03-09T10:42:41.943Z","activatedAt":"2026-03-09T10:42:41.943Z","gracePeriodEnd":null,"sponsorId":"1000001","parentId":"6369838","position":"right","level":0,"directCount":0,"totalEarnings":0,"isCapped":false,"capLevel":0,"reEntryCount":0,"cycleCount":0,"requiredDirectForNextLevel":2,"completedDirectForCurrentLevel":0,"transactionPassword":"1234","emailVerified":false,"achievements":{"nationalTour":false,"internationalTour":false,"familyTour":false}},
  {"id":"user_1773052962181_30","userId":"9030820","email":"admin.bulk.1000001.1773052961477.30@auto.local","password":"user123","fullName":"Member 031","phone":"6218130562","country":"India","isActive":true,"isAdmin":false,"accountStatus":"active","blockedAt":null,"blockedUntil":null,"blockedReason":null,"createdAt":"2026-03-09T10:42:42.181Z","activatedAt":"2026-03-09T10:42:42.181Z","gracePeriodEnd":null,"sponsorId":"1000001","parentId":"4941364","position":"left","level":0,"directCount":0,"totalEarnings":0,"isCapped":false,"capLevel":0,"reEntryCount":0,"cycleCount":0,"requiredDirectForNextLevel":2,"completedDirectForCurrentLevel":0,"transactionPassword":"1234","emailVerified":false,"achievements":{"nationalTour":false,"internationalTour":false,"familyTour":false}},
  {"id":"user_1773052962182_31","userId":"7176961","email":"admin.bulk.1000001.1773052961477.31@auto.local","password":"user123","fullName":"Member 032","phone":"9621823147","country":"India","isActive":true,"isAdmin":false,"accountStatus":"active","blockedAt":null,"blockedUntil":null,"blockedReason":null,"createdAt":"2026-03-09T10:42:42.182Z","activatedAt":"2026-03-09T10:42:42.182Z","gracePeriodEnd":null,"sponsorId":"1000001","parentId":"4941364","position":"right","level":0,"directCount":0,"totalEarnings":0,"isCapped":false,"capLevel":0,"reEntryCount":0,"cycleCount":0,"requiredDirectForNextLevel":2,"completedDirectForCurrentLevel":0,"transactionPassword":"1234","emailVerified":false,"achievements":{"nationalTour":false,"internationalTour":false,"familyTour":false}},
  {"id":"user_1773052962195_32","userId":"5666087","email":"admin.bulk.1000001.1773052961477.32@auto.local","password":"user123","fullName":"Member 033","phone":"6219532651","country":"India","isActive":true,"isAdmin":false,"accountStatus":"active","blockedAt":null,"blockedUntil":null,"blockedReason":null,"createdAt":"2026-03-09T10:42:42.195Z","activatedAt":"2026-03-09T10:42:42.195Z","gracePeriodEnd":null,"sponsorId":"1000001","parentId":"3535377","position":"left","level":0,"directCount":0,"totalEarnings":0,"isCapped":false,"capLevel":0,"reEntryCount":0,"cycleCount":0,"requiredDirectForNextLevel":2,"completedDirectForCurrentLevel":0,"transactionPassword":"1234","emailVerified":false,"achievements":{"nationalTour":false,"internationalTour":false,"familyTour":false}},
  {"id":"user_1773052962196_33","userId":"5762015","email":"admin.bulk.1000001.1773052961477.33@auto.local","password":"user123","fullName":"Member 034","phone":"6219633271","country":"India","isActive":true,"isAdmin":false,"accountStatus":"active","blockedAt":null,"blockedUntil":null,"blockedReason":null,"createdAt":"2026-03-09T10:42:42.196Z","activatedAt":"2026-03-09T10:42:42.196Z","gracePeriodEnd":null,"sponsorId":"1000001","parentId":"3535377","position":"right","level":0,"directCount":0,"totalEarnings":0,"isCapped":false,"capLevel":0,"reEntryCount":0,"cycleCount":0,"requiredDirectForNextLevel":2,"completedDirectForCurrentLevel":0,"transactionPassword":"1234","emailVerified":false,"achievements":{"nationalTour":false,"internationalTour":false,"familyTour":false}},
  {"id":"user_1773052962197_34","userId":"6222935","email":"admin.bulk.1000001.1773052961477.34@auto.local","password":"user123","fullName":"Member 035","phone":"6219734513","country":"India","isActive":true,"isAdmin":false,"accountStatus":"active","blockedAt":null,"blockedUntil":null,"blockedReason":null,"createdAt":"2026-03-09T10:42:42.197Z","activatedAt":"2026-03-09T10:42:42.197Z","gracePeriodEnd":null,"sponsorId":"1000001","parentId":"3315481","position":"left","level":0,"directCount":0,"totalEarnings":0,"isCapped":false,"capLevel":0,"reEntryCount":0,"cycleCount":0,"requiredDirectForNextLevel":2,"completedDirectForCurrentLevel":0,"transactionPassword":"1234","emailVerified":false,"achievements":{"nationalTour":false,"internationalTour":false,"familyTour":false}},
  {"id":"user_1773052962197_35","userId":"4618200","email":"admin.bulk.1000001.1773052961477.35@auto.local","password":"user123","fullName":"Member 036","phone":"6219735857","country":"India","isActive":true,"isAdmin":false,"accountStatus":"active","blockedAt":null,"blockedUntil":null,"blockedReason":null,"createdAt":"2026-03-09T10:42:42.197Z","activatedAt":"2026-03-09T10:42:42.197Z","gracePeriodEnd":null,"sponsorId":"1000001","parentId":"3315481","position":"right","level":0,"directCount":0,"totalEarnings":0,"isCapped":false,"capLevel":0,"reEntryCount":0,"cycleCount":0,"requiredDirectForNextLevel":2,"completedDirectForCurrentLevel":0,"transactionPassword":"1234","emailVerified":false,"achievements":{"nationalTour":false,"internationalTour":false,"familyTour":false}},
  {"id":"user_1773052962198_36","userId":"7710297","email":"admin.bulk.1000001.1773052961477.36@auto.local","password":"user123","fullName":"Member 037","phone":"6219836300","country":"India","isActive":true,"isAdmin":false,"accountStatus":"active","blockedAt":null,"blockedUntil":null,"blockedReason":null,"createdAt":"2026-03-09T10:42:42.198Z","activatedAt":"2026-03-09T10:42:42.198Z","gracePeriodEnd":null,"sponsorId":"1000001","parentId":"9891686","position":"left","level":0,"directCount":0,"totalEarnings":0,"isCapped":false,"capLevel":0,"reEntryCount":0,"cycleCount":0,"requiredDirectForNextLevel":2,"completedDirectForCurrentLevel":0,"transactionPassword":"1234","emailVerified":false,"achievements":{"nationalTour":false,"internationalTour":false,"familyTour":false}},
  {"id":"user_1773052962198_37","userId":"1376236","email":"admin.bulk.1000001.1773052961477.37@auto.local","password":"user123","fullName":"Member 038","phone":"6219837415","country":"India","isActive":true,"isAdmin":false,"accountStatus":"active","blockedAt":null,"blockedUntil":null,"blockedReason":null,"createdAt":"2026-03-09T10:42:42.198Z","activatedAt":"2026-03-09T10:42:42.198Z","gracePeriodEnd":null,"sponsorId":"1000001","parentId":"9891686","position":"right","level":0,"directCount":0,"totalEarnings":0,"isCapped":false,"capLevel":0,"reEntryCount":0,"cycleCount":0,"requiredDirectForNextLevel":2,"completedDirectForCurrentLevel":0,"transactionPassword":"1234","emailVerified":false,"achievements":{"nationalTour":false,"internationalTour":false,"familyTour":false}},
  {"id":"user_1773052962199_38","userId":"7032784","email":"admin.bulk.1000001.1773052961477.38@auto.local","password":"user123","fullName":"Member 039","phone":"6219938470","country":"India","isActive":true,"isAdmin":false,"accountStatus":"active","blockedAt":null,"blockedUntil":null,"blockedReason":null,"createdAt":"2026-03-09T10:42:42.199Z","activatedAt":"2026-03-09T10:42:42.199Z","gracePeriodEnd":null,"sponsorId":"1000001","parentId":"2901818","position":"left","level":0,"directCount":0,"totalEarnings":0,"isCapped":false,"capLevel":0,"reEntryCount":0,"cycleCount":0,"requiredDirectForNextLevel":2,"completedDirectForCurrentLevel":0,"transactionPassword":"1234","emailVerified":false,"achievements":{"nationalTour":false,"internationalTour":false,"familyTour":false}},
  {"id":"user_1773052962200_39","userId":"4318773","email":"admin.bulk.1000001.1773052961477.39@auto.local","password":"user123","fullName":"Member 040","phone":"6220039267","country":"India","isActive":true,"isAdmin":false,"accountStatus":"active","blockedAt":null,"blockedUntil":null,"blockedReason":null,"createdAt":"2026-03-09T10:42:42.200Z","activatedAt":"2026-03-09T10:42:42.200Z","gracePeriodEnd":null,"sponsorId":"1000001","parentId":"2901818","position":"right","level":0,"directCount":0,"totalEarnings":0,"isCapped":false,"capLevel":0,"reEntryCount":0,"cycleCount":0,"requiredDirectForNextLevel":2,"completedDirectForCurrentLevel":0,"transactionPassword":"1234","emailVerified":false,"achievements":{"nationalTour":false,"internationalTour":false,"familyTour":false}},
  {"id":"user_1773052962363_40","userId":"4001554","email":"admin.bulk.1000001.1773052961477.40@auto.local","password":"user123","fullName":"Member 041","phone":"6236340990","country":"India","isActive":true,"isAdmin":false,"accountStatus":"active","blockedAt":null,"blockedUntil":null,"blockedReason":null,"createdAt":"2026-03-09T10:42:42.363Z","activatedAt":"2026-03-09T10:42:42.363Z","gracePeriodEnd":null,"sponsorId":"1000001","parentId":"4173921","position":"left","level":0,"directCount":0,"totalEarnings":0,"isCapped":false,"capLevel":0,"reEntryCount":0,"cycleCount":0,"requiredDirectForNextLevel":2,"completedDirectForCurrentLevel":0,"transactionPassword":"1234","emailVerified":false,"achievements":{"nationalTour":false,"internationalTour":false,"familyTour":false}},
  {"id":"user_1773052962363_41","userId":"5068040","email":"admin.bulk.1000001.1773052961477.41@auto.local","password":"user123","fullName":"Member 042","phone":"6236341374","country":"India","isActive":true,"isAdmin":false,"accountStatus":"active","blockedAt":null,"blockedUntil":null,"blockedReason":null,"createdAt":"2026-03-09T10:42:42.363Z","activatedAt":"2026-03-09T10:42:42.363Z","gracePeriodEnd":null,"sponsorId":"1000001","parentId":"4173921","position":"right","level":0,"directCount":0,"totalEarnings":0,"isCapped":false,"capLevel":0,"reEntryCount":0,"cycleCount":0,"requiredDirectForNextLevel":2,"completedDirectForCurrentLevel":0,"transactionPassword":"1234","emailVerified":false,"achievements":{"nationalTour":false,"internationalTour":false,"familyTour":false}},
  {"id":"user_1773052962365_42","userId":"3863373","email":"admin.bulk.1000001.1773052961477.42@auto.local","password":"user123","fullName":"Member 043","phone":"9623654256","country":"India","isActive":true,"isAdmin":false,"accountStatus":"active","blockedAt":null,"blockedUntil":null,"blockedReason":null,"createdAt":"2026-03-09T10:42:42.365Z","activatedAt":"2026-03-09T10:42:42.365Z","gracePeriodEnd":null,"sponsorId":"1000001","parentId":"4130042","position":"left","level":0,"directCount":0,"totalEarnings":0,"isCapped":false,"capLevel":0,"reEntryCount":0,"cycleCount":0,"requiredDirectForNextLevel":2,"completedDirectForCurrentLevel":0,"transactionPassword":"1234","emailVerified":false,"achievements":{"nationalTour":false,"internationalTour":false,"familyTour":false}},
  {"id":"user_1773052962366_43","userId":"8081104","email":"admin.bulk.1000001.1773052961477.43@auto.local","password":"user123","fullName":"Member 044","phone":"6236643134","country":"India","isActive":true,"isAdmin":false,"accountStatus":"active","blockedAt":null,"blockedUntil":null,"blockedReason":null,"createdAt":"2026-03-09T10:42:42.366Z","activatedAt":"2026-03-09T10:42:42.366Z","gracePeriodEnd":null,"sponsorId":"1000001","parentId":"4130042","position":"right","level":0,"directCount":0,"totalEarnings":0,"isCapped":false,"capLevel":0,"reEntryCount":0,"cycleCount":0,"requiredDirectForNextLevel":2,"completedDirectForCurrentLevel":0,"transactionPassword":"1234","emailVerified":false,"achievements":{"nationalTour":false,"internationalTour":false,"familyTour":false}},
  {"id":"user_1773052962367_44","userId":"8469337","email":"admin.bulk.1000001.1773052961477.44@auto.local","password":"user123","fullName":"Member 045","phone":"6236744947","country":"India","isActive":true,"isAdmin":false,"accountStatus":"active","blockedAt":null,"blockedUntil":null,"blockedReason":null,"createdAt":"2026-03-09T10:42:42.367Z","activatedAt":"2026-03-09T10:42:42.367Z","gracePeriodEnd":null,"sponsorId":"1000001","parentId":"9671746","position":"left","level":0,"directCount":0,"totalEarnings":0,"isCapped":false,"capLevel":0,"reEntryCount":0,"cycleCount":0,"requiredDirectForNextLevel":2,"completedDirectForCurrentLevel":0,"transactionPassword":"1234","emailVerified":false,"achievements":{"nationalTour":false,"internationalTour":false,"familyTour":false}},
  {"id":"user_1773052962368_45","userId":"7466908","email":"admin.bulk.1000001.1773052961477.45@auto.local","password":"user123","fullName":"Member 046","phone":"9623684528","country":"India","isActive":true,"isAdmin":false,"accountStatus":"active","blockedAt":null,"blockedUntil":null,"blockedReason":null,"createdAt":"2026-03-09T10:42:42.368Z","activatedAt":"2026-03-09T10:42:42.368Z","gracePeriodEnd":null,"sponsorId":"1000001","parentId":"9671746","position":"right","level":0,"directCount":0,"totalEarnings":0,"isCapped":false,"capLevel":0,"reEntryCount":0,"cycleCount":0,"requiredDirectForNextLevel":2,"completedDirectForCurrentLevel":0,"transactionPassword":"1234","emailVerified":false,"achievements":{"nationalTour":false,"internationalTour":false,"familyTour":false}},
  {"id":"user_1773052962369_46","userId":"6795355","email":"admin.bulk.1000001.1773052961477.46@auto.local","password":"user123","fullName":"Member 047","phone":"6236946740","country":"India","isActive":true,"isAdmin":false,"accountStatus":"active","blockedAt":null,"blockedUntil":null,"blockedReason":null,"createdAt":"2026-03-09T10:42:42.369Z","activatedAt":"2026-03-09T10:42:42.369Z","gracePeriodEnd":null,"sponsorId":"1000001","parentId":"5148139","position":"left","level":0,"directCount":0,"totalEarnings":0,"isCapped":false,"capLevel":0,"reEntryCount":0,"cycleCount":0,"requiredDirectForNextLevel":2,"completedDirectForCurrentLevel":0,"transactionPassword":"1234","emailVerified":false,"achievements":{"nationalTour":false,"internationalTour":false,"familyTour":false}},
  {"id":"user_1773052962369_47","userId":"4927255","email":"admin.bulk.1000001.1773052961477.47@auto.local","password":"user123","fullName":"Member 048","phone":"6236947584","country":"India","isActive":true,"isAdmin":false,"accountStatus":"active","blockedAt":null,"blockedUntil":null,"blockedReason":null,"createdAt":"2026-03-09T10:42:42.369Z","activatedAt":"2026-03-09T10:42:42.369Z","gracePeriodEnd":null,"sponsorId":"1000001","parentId":"5148139","position":"right","level":0,"directCount":0,"totalEarnings":0,"isCapped":false,"capLevel":0,"reEntryCount":0,"cycleCount":0,"requiredDirectForNextLevel":2,"completedDirectForCurrentLevel":0,"transactionPassword":"1234","emailVerified":false,"achievements":{"nationalTour":false,"internationalTour":false,"familyTour":false}},
  {"id":"user_1773052962370_48","userId":"3750316","email":"admin.bulk.1000001.1773052961477.48@auto.local","password":"user123","fullName":"Member 049","phone":"9623704859","country":"India","isActive":true,"isAdmin":false,"accountStatus":"active","blockedAt":null,"blockedUntil":null,"blockedReason":null,"createdAt":"2026-03-09T10:42:42.370Z","activatedAt":"2026-03-09T10:42:42.370Z","gracePeriodEnd":null,"sponsorId":"1000001","parentId":"5488566","position":"left","level":0,"directCount":0,"totalEarnings":0,"isCapped":false,"capLevel":0,"reEntryCount":0,"cycleCount":0,"requiredDirectForNextLevel":2,"completedDirectForCurrentLevel":0,"transactionPassword":"1234","emailVerified":false,"achievements":{"nationalTour":false,"internationalTour":false,"familyTour":false}},
  {"id":"user_1773052962370_49","userId":"8287897","email":"admin.bulk.1000001.1773052961477.49@auto.local","password":"user123","fullName":"Member 050","phone":"6237049965","country":"India","isActive":true,"isAdmin":false,"accountStatus":"active","blockedAt":null,"blockedUntil":null,"blockedReason":null,"createdAt":"2026-03-09T10:42:42.370Z","activatedAt":"2026-03-09T10:42:42.370Z","gracePeriodEnd":null,"sponsorId":"1000001","parentId":"5488566","position":"right","level":0,"directCount":0,"totalEarnings":0,"isCapped":false,"capLevel":0,"reEntryCount":0,"cycleCount":0,"requiredDirectForNextLevel":2,"completedDirectForCurrentLevel":0,"transactionPassword":"1234","emailVerified":false,"achievements":{"nationalTour":false,"internationalTour":false,"familyTour":false}},
  {"id":"user_1773052962391_50","userId":"9754389","email":"admin.bulk.1000001.1773052961477.50@auto.local","password":"user123","fullName":"Member 051","phone":"6239150554","country":"India","isActive":true,"isAdmin":false,"accountStatus":"active","blockedAt":null,"blockedUntil":null,"blockedReason":null,"createdAt":"2026-03-09T10:42:42.391Z","activatedAt":"2026-03-09T10:42:42.391Z","gracePeriodEnd":null,"sponsorId":"1000001","parentId":"2782991","position":"left","level":0,"directCount":0,"totalEarnings":0,"isCapped":false,"capLevel":0,"reEntryCount":0,"cycleCount":0,"requiredDirectForNextLevel":2,"completedDirectForCurrentLevel":0,"transactionPassword":"1234","emailVerified":false,"achievements":{"nationalTour":false,"internationalTour":false,"familyTour":false}},
  {"id":"user_1773052962392_51","userId":"5410253","email":"admin.bulk.1000001.1773052961477.51@auto.local","password":"user123","fullName":"Member 052","phone":"6239251885","country":"India","isActive":true,"isAdmin":false,"accountStatus":"active","blockedAt":null,"blockedUntil":null,"blockedReason":null,"createdAt":"2026-03-09T10:42:42.392Z","activatedAt":"2026-03-09T10:42:42.392Z","gracePeriodEnd":null,"sponsorId":"1000001","parentId":"2782991","position":"right","level":0,"directCount":0,"totalEarnings":0,"isCapped":false,"capLevel":0,"reEntryCount":0,"cycleCount":0,"requiredDirectForNextLevel":2,"completedDirectForCurrentLevel":0,"transactionPassword":"1234","emailVerified":false,"achievements":{"nationalTour":false,"internationalTour":false,"familyTour":false}},
  {"id":"user_1773052962394_52","userId":"5622959","email":"admin.bulk.1000001.1773052961477.52@auto.local","password":"user123","fullName":"Member 053","phone":"6239452891","country":"India","isActive":true,"isAdmin":false,"accountStatus":"active","blockedAt":null,"blockedUntil":null,"blockedReason":null,"createdAt":"2026-03-09T10:42:42.394Z","activatedAt":"2026-03-09T10:42:42.394Z","gracePeriodEnd":null,"sponsorId":"1000001","parentId":"1442967","position":"left","level":0,"directCount":0,"totalEarnings":0,"isCapped":false,"capLevel":0,"reEntryCount":0,"cycleCount":0,"requiredDirectForNextLevel":2,"completedDirectForCurrentLevel":0,"transactionPassword":"1234","emailVerified":false,"achievements":{"nationalTour":false,"internationalTour":false,"familyTour":false}},
  {"id":"user_1773052962395_53","userId":"8213766","email":"admin.bulk.1000001.1773052961477.53@auto.local","password":"user123","fullName":"Member 054","phone":"6239553417","country":"India","isActive":true,"isAdmin":false,"accountStatus":"active","blockedAt":null,"blockedUntil":null,"blockedReason":null,"createdAt":"2026-03-09T10:42:42.395Z","activatedAt":"2026-03-09T10:42:42.395Z","gracePeriodEnd":null,"sponsorId":"1000001","parentId":"1442967","position":"right","level":0,"directCount":0,"totalEarnings":0,"isCapped":false,"capLevel":0,"reEntryCount":0,"cycleCount":0,"requiredDirectForNextLevel":2,"completedDirectForCurrentLevel":0,"transactionPassword":"1234","emailVerified":false,"achievements":{"nationalTour":false,"internationalTour":false,"familyTour":false}},
  {"id":"user_1773052962397_54","userId":"8575766","email":"admin.bulk.1000001.1773052961477.54@auto.local","password":"user123","fullName":"Member 055","phone":"6239754653","country":"India","isActive":true,"isAdmin":false,"accountStatus":"active","blockedAt":null,"blockedUntil":null,"blockedReason":null,"createdAt":"2026-03-09T10:42:42.397Z","activatedAt":"2026-03-09T10:42:42.397Z","gracePeriodEnd":null,"sponsorId":"1000001","parentId":"5565441","position":"left","level":0,"directCount":0,"totalEarnings":0,"isCapped":false,"capLevel":0,"reEntryCount":0,"cycleCount":0,"requiredDirectForNextLevel":2,"completedDirectForCurrentLevel":0,"transactionPassword":"1234","emailVerified":false,"achievements":{"nationalTour":false,"internationalTour":false,"familyTour":false}},
  {"id":"user_1773052962398_55","userId":"2744788","email":"admin.bulk.1000001.1773052961477.55@auto.local","password":"user123","fullName":"Member 056","phone":"6239855494","country":"India","isActive":true,"isAdmin":false,"accountStatus":"active","blockedAt":null,"blockedUntil":null,"blockedReason":null,"createdAt":"2026-03-09T10:42:42.398Z","activatedAt":"2026-03-09T10:42:42.398Z","gracePeriodEnd":null,"sponsorId":"1000001","parentId":"5565441","position":"right","level":0,"directCount":0,"totalEarnings":0,"isCapped":false,"capLevel":0,"reEntryCount":0,"cycleCount":0,"requiredDirectForNextLevel":2,"completedDirectForCurrentLevel":0,"transactionPassword":"1234","emailVerified":false,"achievements":{"nationalTour":false,"internationalTour":false,"familyTour":false}},
  {"id":"user_1773052962399_56","userId":"4836182","email":"admin.bulk.1000001.1773052961477.56@auto.local","password":"user123","fullName":"Member 057","phone":"6239956390","country":"India","isActive":true,"isAdmin":false,"accountStatus":"active","blockedAt":null,"blockedUntil":null,"blockedReason":null,"createdAt":"2026-03-09T10:42:42.399Z","activatedAt":"2026-03-09T10:42:42.399Z","gracePeriodEnd":null,"sponsorId":"1000001","parentId":"7959608","position":"left","level":0,"directCount":0,"totalEarnings":0,"isCapped":false,"capLevel":0,"reEntryCount":0,"cycleCount":0,"requiredDirectForNextLevel":2,"completedDirectForCurrentLevel":0,"transactionPassword":"1234","emailVerified":false,"achievements":{"nationalTour":false,"internationalTour":false,"familyTour":false}},
  {"id":"user_1773052962399_57","userId":"7090468","email":"admin.bulk.1000001.1773052961477.57@auto.local","password":"user123","fullName":"Member 058","phone":"6239957751","country":"India","isActive":true,"isAdmin":false,"accountStatus":"active","blockedAt":null,"blockedUntil":null,"blockedReason":null,"createdAt":"2026-03-09T10:42:42.399Z","activatedAt":"2026-03-09T10:42:42.399Z","gracePeriodEnd":null,"sponsorId":"1000001","parentId":"7959608","position":"right","level":0,"directCount":0,"totalEarnings":0,"isCapped":false,"capLevel":0,"reEntryCount":0,"cycleCount":0,"requiredDirectForNextLevel":2,"completedDirectForCurrentLevel":0,"transactionPassword":"1234","emailVerified":false,"achievements":{"nationalTour":false,"internationalTour":false,"familyTour":false}},
  {"id":"user_1773052962400_58","userId":"9608853","email":"admin.bulk.1000001.1773052961477.58@auto.local","password":"user123","fullName":"Member 059","phone":"6240058429","country":"India","isActive":true,"isAdmin":false,"accountStatus":"active","blockedAt":null,"blockedUntil":null,"blockedReason":null,"createdAt":"2026-03-09T10:42:42.400Z","activatedAt":"2026-03-09T10:42:42.400Z","gracePeriodEnd":null,"sponsorId":"1000001","parentId":"6184215","position":"left","level":0,"directCount":0,"totalEarnings":0,"isCapped":false,"capLevel":0,"reEntryCount":0,"cycleCount":0,"requiredDirectForNextLevel":2,"completedDirectForCurrentLevel":0,"transactionPassword":"1234","emailVerified":false,"achievements":{"nationalTour":false,"internationalTour":false,"familyTour":false}},
  {"id":"user_1773052962401_59","userId":"9824649","email":"admin.bulk.1000001.1773052961477.59@auto.local","password":"user123","fullName":"Member 060","phone":"6240159887","country":"India","isActive":true,"isAdmin":false,"accountStatus":"active","blockedAt":null,"blockedUntil":null,"blockedReason":null,"createdAt":"2026-03-09T10:42:42.401Z","activatedAt":"2026-03-09T10:42:42.401Z","gracePeriodEnd":null,"sponsorId":"1000001","parentId":"6184215","position":"right","level":0,"directCount":0,"totalEarnings":0,"isCapped":false,"capLevel":0,"reEntryCount":0,"cycleCount":0,"requiredDirectForNextLevel":2,"completedDirectForCurrentLevel":0,"transactionPassword":"1234","emailVerified":false,"achievements":{"nationalTour":false,"internationalTour":false,"familyTour":false}},
  {"id":"user_1773052962425_60","userId":"2808472","email":"admin.bulk.1000001.1773052961477.60@auto.local","password":"user123","fullName":"Member 061","phone":"6242560357","country":"India","isActive":true,"isAdmin":false,"accountStatus":"active","blockedAt":null,"blockedUntil":null,"blockedReason":null,"createdAt":"2026-03-09T10:42:42.425Z","activatedAt":"2026-03-09T10:42:42.425Z","gracePeriodEnd":null,"sponsorId":"1000001","parentId":"3251493","position":"left","level":0,"directCount":0,"totalEarnings":0,"isCapped":false,"capLevel":0,"reEntryCount":0,"cycleCount":0,"requiredDirectForNextLevel":2,"completedDirectForCurrentLevel":0,"transactionPassword":"1234","emailVerified":false,"achievements":{"nationalTour":false,"internationalTour":false,"familyTour":false}},
  {"id":"user_1773052962427_61","userId":"4787884","email":"admin.bulk.1000001.1773052961477.61@auto.local","password":"user123","fullName":"Member 062","phone":"6242761933","country":"India","isActive":true,"isAdmin":false,"accountStatus":"active","blockedAt":null,"blockedUntil":null,"blockedReason":null,"createdAt":"2026-03-09T10:42:42.427Z","activatedAt":"2026-03-09T10:42:42.427Z","gracePeriodEnd":null,"sponsorId":"1000001","parentId":"3251493","position":"right","level":0,"directCount":0,"totalEarnings":0,"isCapped":false,"capLevel":0,"reEntryCount":0,"cycleCount":0,"requiredDirectForNextLevel":2,"completedDirectForCurrentLevel":0,"transactionPassword":"1234","emailVerified":false,"achievements":{"nationalTour":false,"internationalTour":false,"familyTour":false}},
  {"id":"user_1773052962428_62","userId":"4903824","email":"admin.bulk.1000001.1773052961477.62@auto.local","password":"user123","fullName":"Member 063","phone":"6242862185","country":"India","isActive":true,"isAdmin":false,"accountStatus":"active","blockedAt":null,"blockedUntil":null,"blockedReason":null,"createdAt":"2026-03-09T10:42:42.428Z","activatedAt":"2026-03-09T10:42:42.428Z","gracePeriodEnd":null,"sponsorId":"1000001","parentId":"9030820","position":"left","level":0,"directCount":0,"totalEarnings":0,"isCapped":false,"capLevel":0,"reEntryCount":0,"cycleCount":0,"requiredDirectForNextLevel":2,"completedDirectForCurrentLevel":0,"transactionPassword":"1234","emailVerified":false,"achievements":{"nationalTour":false,"internationalTour":false,"familyTour":false}},
  {"id":"user_1773052962428_63","userId":"4605171","email":"admin.bulk.1000001.1773052961477.63@auto.local","password":"user123","fullName":"Member 064","phone":"9624286343","country":"India","isActive":true,"isAdmin":false,"accountStatus":"active","blockedAt":null,"blockedUntil":null,"blockedReason":null,"createdAt":"2026-03-09T10:42:42.428Z","activatedAt":"2026-03-09T10:42:42.428Z","gracePeriodEnd":null,"sponsorId":"1000001","parentId":"9030820","position":"right","level":0,"directCount":0,"totalEarnings":0,"isCapped":false,"capLevel":0,"reEntryCount":0,"cycleCount":0,"requiredDirectForNextLevel":2,"completedDirectForCurrentLevel":0,"transactionPassword":"1234","emailVerified":false,"achievements":{"nationalTour":false,"internationalTour":false,"familyTour":false}},
  {"id":"user_1773052962429_64","userId":"4526069","email":"admin.bulk.1000001.1773052961477.64@auto.local","password":"user123","fullName":"Member 065","phone":"6242964339","country":"India","isActive":true,"isAdmin":false,"accountStatus":"active","blockedAt":null,"blockedUntil":null,"blockedReason":null,"createdAt":"2026-03-09T10:42:42.429Z","activatedAt":"2026-03-09T10:42:42.429Z","gracePeriodEnd":null,"sponsorId":"1000001","parentId":"7176961","position":"left","level":0,"directCount":0,"totalEarnings":0,"isCapped":false,"capLevel":0,"reEntryCount":0,"cycleCount":0,"requiredDirectForNextLevel":2,"completedDirectForCurrentLevel":0,"transactionPassword":"1234","emailVerified":false,"achievements":{"nationalTour":false,"internationalTour":false,"familyTour":false}},
  {"id":"user_1773052962430_65","userId":"9781323","email":"admin.bulk.1000001.1773052961477.65@auto.local","password":"user123","fullName":"Member 066","phone":"6243065495","country":"India","isActive":true,"isAdmin":false,"accountStatus":"active","blockedAt":null,"blockedUntil":null,"blockedReason":null,"createdAt":"2026-03-09T10:42:42.430Z","activatedAt":"2026-03-09T10:42:42.430Z","gracePeriodEnd":null,"sponsorId":"1000001","parentId":"7176961","position":"right","level":0,"directCount":0,"totalEarnings":0,"isCapped":false,"capLevel":0,"reEntryCount":0,"cycleCount":0,"requiredDirectForNextLevel":2,"completedDirectForCurrentLevel":0,"transactionPassword":"1234","emailVerified":false,"achievements":{"nationalTour":false,"internationalTour":false,"familyTour":false}},
  {"id":"user_1773052962432_66","userId":"8875619","email":"admin.bulk.1000001.1773052961477.66@auto.local","password":"user123","fullName":"Member 067","phone":"6243266404","country":"India","isActive":true,"isAdmin":false,"accountStatus":"active","blockedAt":null,"blockedUntil":null,"blockedReason":null,"createdAt":"2026-03-09T10:42:42.432Z","activatedAt":"2026-03-09T10:42:42.432Z","gracePeriodEnd":null,"sponsorId":"1000001","parentId":"5666087","position":"left","level":0,"directCount":0,"totalEarnings":0,"isCapped":false,"capLevel":0,"reEntryCount":0,"cycleCount":0,"requiredDirectForNextLevel":2,"completedDirectForCurrentLevel":0,"transactionPassword":"1234","emailVerified":false,"achievements":{"nationalTour":false,"internationalTour":false,"familyTour":false}},
  {"id":"user_1773052962433_67","userId":"1919994","email":"admin.bulk.1000001.1773052961477.67@auto.local","password":"user123","fullName":"Member 068","phone":"6243367404","country":"India","isActive":true,"isAdmin":false,"accountStatus":"active","blockedAt":null,"blockedUntil":null,"blockedReason":null,"createdAt":"2026-03-09T10:42:42.433Z","activatedAt":"2026-03-09T10:42:42.433Z","gracePeriodEnd":null,"sponsorId":"1000001","parentId":"5666087","position":"right","level":0,"directCount":0,"totalEarnings":0,"isCapped":false,"capLevel":0,"reEntryCount":0,"cycleCount":0,"requiredDirectForNextLevel":2,"completedDirectForCurrentLevel":0,"transactionPassword":"1234","emailVerified":false,"achievements":{"nationalTour":false,"internationalTour":false,"familyTour":false}},
  {"id":"user_1773052962434_68","userId":"9624159","email":"admin.bulk.1000001.1773052961477.68@auto.local","password":"user123","fullName":"Member 069","phone":"6243468685","country":"India","isActive":true,"isAdmin":false,"accountStatus":"active","blockedAt":null,"blockedUntil":null,"blockedReason":null,"createdAt":"2026-03-09T10:42:42.434Z","activatedAt":"2026-03-09T10:42:42.434Z","gracePeriodEnd":null,"sponsorId":"1000001","parentId":"5762015","position":"left","level":0,"directCount":0,"totalEarnings":0,"isCapped":false,"capLevel":0,"reEntryCount":0,"cycleCount":0,"requiredDirectForNextLevel":2,"completedDirectForCurrentLevel":0,"transactionPassword":"1234","emailVerified":false,"achievements":{"nationalTour":false,"internationalTour":false,"familyTour":false}},
  {"id":"user_1773052962434_69","userId":"6345429","email":"admin.bulk.1000001.1773052961477.69@auto.local","password":"user123","fullName":"Member 070","phone":"6243469814","country":"India","isActive":true,"isAdmin":false,"accountStatus":"active","blockedAt":null,"blockedUntil":null,"blockedReason":null,"createdAt":"2026-03-09T10:42:42.434Z","activatedAt":"2026-03-09T10:42:42.434Z","gracePeriodEnd":null,"sponsorId":"1000001","parentId":"5762015","position":"right","level":0,"directCount":0,"totalEarnings":0,"isCapped":false,"capLevel":0,"reEntryCount":0,"cycleCount":0,"requiredDirectForNextLevel":2,"completedDirectForCurrentLevel":0,"transactionPassword":"1234","emailVerified":false,"achievements":{"nationalTour":false,"internationalTour":false,"familyTour":false}},
  {"id":"user_1773052962460_70","userId":"6949119","email":"admin.bulk.1000001.1773052961477.70@auto.local","password":"user123","fullName":"Member 071","phone":"6246070716","country":"India","isActive":true,"isAdmin":false,"accountStatus":"active","blockedAt":null,"blockedUntil":null,"blockedReason":null,"createdAt":"2026-03-09T10:42:42.460Z","activatedAt":"2026-03-09T10:42:42.460Z","gracePeriodEnd":null,"sponsorId":"1000001","parentId":"6222935","position":"left","level":0,"directCount":0,"totalEarnings":0,"isCapped":false,"capLevel":0,"reEntryCount":0,"cycleCount":0,"requiredDirectForNextLevel":2,"completedDirectForCurrentLevel":0,"transactionPassword":"1234","emailVerified":false,"achievements":{"nationalTour":false,"internationalTour":false,"familyTour":false}},
  {"id":"user_1773052962461_71","userId":"4876557","email":"admin.bulk.1000001.1773052961477.71@auto.local","password":"user123","fullName":"Member 072","phone":"6246171463","country":"India","isActive":true,"isAdmin":false,"accountStatus":"active","blockedAt":null,"blockedUntil":null,"blockedReason":null,"createdAt":"2026-03-09T10:42:42.461Z","activatedAt":"2026-03-09T10:42:42.461Z","gracePeriodEnd":null,"sponsorId":"1000001","parentId":"6222935","position":"right","level":0,"directCount":0,"totalEarnings":0,"isCapped":false,"capLevel":0,"reEntryCount":0,"cycleCount":0,"requiredDirectForNextLevel":2,"completedDirectForCurrentLevel":0,"transactionPassword":"1234","emailVerified":false,"achievements":{"nationalTour":false,"internationalTour":false,"familyTour":false}},
  {"id":"user_1773052962462_72","userId":"7107202","email":"admin.bulk.1000001.1773052961477.72@auto.local","password":"user123","fullName":"Member 073","phone":"6246272362","country":"India","isActive":true,"isAdmin":false,"accountStatus":"active","blockedAt":null,"blockedUntil":null,"blockedReason":null,"createdAt":"2026-03-09T10:42:42.462Z","activatedAt":"2026-03-09T10:42:42.462Z","gracePeriodEnd":null,"sponsorId":"1000001","parentId":"4618200","position":"left","level":0,"directCount":0,"totalEarnings":0,"isCapped":false,"capLevel":0,"reEntryCount":0,"cycleCount":0,"requiredDirectForNextLevel":2,"completedDirectForCurrentLevel":0,"transactionPassword":"1234","emailVerified":false,"achievements":{"nationalTour":false,"internationalTour":false,"familyTour":false}},
  {"id":"user_1773052962463_73","userId":"5438394","email":"admin.bulk.1000001.1773052961477.73@auto.local","password":"user123","fullName":"Member 074","phone":"6246373922","country":"India","isActive":true,"isAdmin":false,"accountStatus":"active","blockedAt":null,"blockedUntil":null,"blockedReason":null,"createdAt":"2026-03-09T10:42:42.463Z","activatedAt":"2026-03-09T10:42:42.463Z","gracePeriodEnd":null,"sponsorId":"1000001","parentId":"4618200","position":"right","level":0,"directCount":0,"totalEarnings":0,"isCapped":false,"capLevel":0,"reEntryCount":0,"cycleCount":0,"requiredDirectForNextLevel":2,"completedDirectForCurrentLevel":0,"transactionPassword":"1234","emailVerified":false,"achievements":{"nationalTour":false,"internationalTour":false,"familyTour":false}},
  {"id":"user_1773052962465_74","userId":"4268700","email":"admin.bulk.1000001.1773052961477.74@auto.local","password":"user123","fullName":"Member 075","phone":"6246574583","country":"India","isActive":true,"isAdmin":false,"accountStatus":"active","blockedAt":null,"blockedUntil":null,"blockedReason":null,"createdAt":"2026-03-09T10:42:42.465Z","activatedAt":"2026-03-09T10:42:42.465Z","gracePeriodEnd":null,"sponsorId":"1000001","parentId":"7710297","position":"left","level":0,"directCount":0,"totalEarnings":0,"isCapped":false,"capLevel":0,"reEntryCount":0,"cycleCount":0,"requiredDirectForNextLevel":2,"completedDirectForCurrentLevel":0,"transactionPassword":"1234","emailVerified":false,"achievements":{"nationalTour":false,"internationalTour":false,"familyTour":false}},
  {"id":"user_1773052962466_75","userId":"6737115","email":"admin.bulk.1000001.1773052961477.75@auto.local","password":"user123","fullName":"Member 076","phone":"6246675142","country":"India","isActive":true,"isAdmin":false,"accountStatus":"active","blockedAt":null,"blockedUntil":null,"blockedReason":null,"createdAt":"2026-03-09T10:42:42.466Z","activatedAt":"2026-03-09T10:42:42.466Z","gracePeriodEnd":null,"sponsorId":"1000001","parentId":"7710297","position":"right","level":0,"directCount":0,"totalEarnings":0,"isCapped":false,"capLevel":0,"reEntryCount":0,"cycleCount":0,"requiredDirectForNextLevel":2,"completedDirectForCurrentLevel":0,"transactionPassword":"1234","emailVerified":false,"achievements":{"nationalTour":false,"internationalTour":false,"familyTour":false}},
  {"id":"user_1773052962467_76","userId":"2175428","email":"admin.bulk.1000001.1773052961477.76@auto.local","password":"user123","fullName":"Member 077","phone":"6246776251","country":"India","isActive":true,"isAdmin":false,"accountStatus":"active","blockedAt":null,"blockedUntil":null,"blockedReason":null,"createdAt":"2026-03-09T10:42:42.467Z","activatedAt":"2026-03-09T10:42:42.467Z","gracePeriodEnd":null,"sponsorId":"1000001","parentId":"1376236","position":"left","level":0,"directCount":0,"totalEarnings":0,"isCapped":false,"capLevel":0,"reEntryCount":0,"cycleCount":0,"requiredDirectForNextLevel":2,"completedDirectForCurrentLevel":0,"transactionPassword":"1234","emailVerified":false,"achievements":{"nationalTour":false,"internationalTour":false,"familyTour":false}},
  {"id":"user_1773052962468_77","userId":"2440282","email":"admin.bulk.1000001.1773052961477.77@auto.local","password":"user123","fullName":"Member 078","phone":"6246877307","country":"India","isActive":true,"isAdmin":false,"accountStatus":"active","blockedAt":null,"blockedUntil":null,"blockedReason":null,"createdAt":"2026-03-09T10:42:42.468Z","activatedAt":"2026-03-09T10:42:42.468Z","gracePeriodEnd":null,"sponsorId":"1000001","parentId":"1376236","position":"right","level":0,"directCount":0,"totalEarnings":0,"isCapped":false,"capLevel":0,"reEntryCount":0,"cycleCount":0,"requiredDirectForNextLevel":2,"completedDirectForCurrentLevel":0,"transactionPassword":"1234","emailVerified":false,"achievements":{"nationalTour":false,"internationalTour":false,"familyTour":false}},
  {"id":"user_1773052962469_78","userId":"3456301","email":"admin.bulk.1000001.1773052961477.78@auto.local","password":"user123","fullName":"Member 079","phone":"6246978911","country":"India","isActive":true,"isAdmin":false,"accountStatus":"active","blockedAt":null,"blockedUntil":null,"blockedReason":null,"createdAt":"2026-03-09T10:42:42.469Z","activatedAt":"2026-03-09T10:42:42.469Z","gracePeriodEnd":null,"sponsorId":"1000001","parentId":"7032784","position":"left","level":0,"directCount":0,"totalEarnings":0,"isCapped":false,"capLevel":0,"reEntryCount":0,"cycleCount":0,"requiredDirectForNextLevel":2,"completedDirectForCurrentLevel":0,"transactionPassword":"1234","emailVerified":false,"achievements":{"nationalTour":false,"internationalTour":false,"familyTour":false}},
  {"id":"user_1773052962470_79","userId":"3239939","email":"admin.bulk.1000001.1773052961477.79@auto.local","password":"user123","fullName":"Member 080","phone":"6247079403","country":"India","isActive":true,"isAdmin":false,"accountStatus":"active","blockedAt":null,"blockedUntil":null,"blockedReason":null,"createdAt":"2026-03-09T10:42:42.470Z","activatedAt":"2026-03-09T10:42:42.470Z","gracePeriodEnd":null,"sponsorId":"1000001","parentId":"7032784","position":"right","level":0,"directCount":0,"totalEarnings":0,"isCapped":false,"capLevel":0,"reEntryCount":0,"cycleCount":0,"requiredDirectForNextLevel":2,"completedDirectForCurrentLevel":0,"transactionPassword":"1234","emailVerified":false,"achievements":{"nationalTour":false,"internationalTour":false,"familyTour":false}},
  {"id":"user_1773052962494_80","userId":"3367076","email":"admin.bulk.1000001.1773052961477.80@auto.local","password":"user123","fullName":"Member 081","phone":"6249480459","country":"India","isActive":true,"isAdmin":false,"accountStatus":"active","blockedAt":null,"blockedUntil":null,"blockedReason":null,"createdAt":"2026-03-09T10:42:42.494Z","activatedAt":"2026-03-09T10:42:42.494Z","gracePeriodEnd":null,"sponsorId":"1000001","parentId":"4318773","position":"left","level":0,"directCount":0,"totalEarnings":0,"isCapped":false,"capLevel":0,"reEntryCount":0,"cycleCount":0,"requiredDirectForNextLevel":2,"completedDirectForCurrentLevel":0,"transactionPassword":"1234","emailVerified":false,"achievements":{"nationalTour":false,"internationalTour":false,"familyTour":false}},
  {"id":"user_1773052962496_81","userId":"5359197","email":"admin.bulk.1000001.1773052961477.81@auto.local","password":"user123","fullName":"Member 082","phone":"6249681905","country":"India","isActive":true,"isAdmin":false,"accountStatus":"active","blockedAt":null,"blockedUntil":null,"blockedReason":null,"createdAt":"2026-03-09T10:42:42.496Z","activatedAt":"2026-03-09T10:42:42.496Z","gracePeriodEnd":null,"sponsorId":"1000001","parentId":"4318773","position":"right","level":0,"directCount":0,"totalEarnings":0,"isCapped":false,"capLevel":0,"reEntryCount":0,"cycleCount":0,"requiredDirectForNextLevel":2,"completedDirectForCurrentLevel":0,"transactionPassword":"1234","emailVerified":false,"achievements":{"nationalTour":false,"internationalTour":false,"familyTour":false}},
  {"id":"user_1773052962498_82","userId":"9632709","email":"admin.bulk.1000001.1773052961477.82@auto.local","password":"user123","fullName":"Member 083","phone":"6249882724","country":"India","isActive":true,"isAdmin":false,"accountStatus":"active","blockedAt":null,"blockedUntil":null,"blockedReason":null,"createdAt":"2026-03-09T10:42:42.498Z","activatedAt":"2026-03-09T10:42:42.498Z","gracePeriodEnd":null,"sponsorId":"1000001","parentId":"4001554","position":"left","level":0,"directCount":0,"totalEarnings":0,"isCapped":false,"capLevel":0,"reEntryCount":0,"cycleCount":0,"requiredDirectForNextLevel":2,"completedDirectForCurrentLevel":0,"transactionPassword":"1234","emailVerified":false,"achievements":{"nationalTour":false,"internationalTour":false,"familyTour":false}},
  {"id":"user_1773052962499_83","userId":"8395865","email":"admin.bulk.1000001.1773052961477.83@auto.local","password":"user123","fullName":"Member 084","phone":"6249983359","country":"India","isActive":true,"isAdmin":false,"accountStatus":"active","blockedAt":null,"blockedUntil":null,"blockedReason":null,"createdAt":"2026-03-09T10:42:42.499Z","activatedAt":"2026-03-09T10:42:42.499Z","gracePeriodEnd":null,"sponsorId":"1000001","parentId":"4001554","position":"right","level":0,"directCount":0,"totalEarnings":0,"isCapped":false,"capLevel":0,"reEntryCount":0,"cycleCount":0,"requiredDirectForNextLevel":2,"completedDirectForCurrentLevel":0,"transactionPassword":"1234","emailVerified":false,"achievements":{"nationalTour":false,"internationalTour":false,"familyTour":false}},
  {"id":"user_1773052962500_84","userId":"7014375","email":"admin.bulk.1000001.1773052961477.84@auto.local","password":"user123","fullName":"Member 085","phone":"6250084364","country":"India","isActive":true,"isAdmin":false,"accountStatus":"active","blockedAt":null,"blockedUntil":null,"blockedReason":null,"createdAt":"2026-03-09T10:42:42.500Z","activatedAt":"2026-03-09T10:42:42.500Z","gracePeriodEnd":null,"sponsorId":"1000001","parentId":"5068040","position":"left","level":0,"directCount":0,"totalEarnings":0,"isCapped":false,"capLevel":0,"reEntryCount":0,"cycleCount":0,"requiredDirectForNextLevel":2,"completedDirectForCurrentLevel":0,"transactionPassword":"1234","emailVerified":false,"achievements":{"nationalTour":false,"internationalTour":false,"familyTour":false}},
  {"id":"user_1773052962501_85","userId":"6677961","email":"admin.bulk.1000001.1773052961477.85@auto.local","password":"user123","fullName":"Member 086","phone":"6250185708","country":"India","isActive":true,"isAdmin":false,"accountStatus":"active","blockedAt":null,"blockedUntil":null,"blockedReason":null,"createdAt":"2026-03-09T10:42:42.501Z","activatedAt":"2026-03-09T10:42:42.501Z","gracePeriodEnd":null,"sponsorId":"1000001","parentId":"5068040","position":"right","level":0,"directCount":0,"totalEarnings":0,"isCapped":false,"capLevel":0,"reEntryCount":0,"cycleCount":0,"requiredDirectForNextLevel":2,"completedDirectForCurrentLevel":0,"transactionPassword":"1234","emailVerified":false,"achievements":{"nationalTour":false,"internationalTour":false,"familyTour":false}},
  {"id":"user_1773052962502_86","userId":"5249542","email":"admin.bulk.1000001.1773052961477.86@auto.local","password":"user123","fullName":"Member 087","phone":"6250286376","country":"India","isActive":true,"isAdmin":false,"accountStatus":"active","blockedAt":null,"blockedUntil":null,"blockedReason":null,"createdAt":"2026-03-09T10:42:42.502Z","activatedAt":"2026-03-09T10:42:42.502Z","gracePeriodEnd":null,"sponsorId":"1000001","parentId":"3863373","position":"left","level":0,"directCount":0,"totalEarnings":0,"isCapped":false,"capLevel":0,"reEntryCount":0,"cycleCount":0,"requiredDirectForNextLevel":2,"completedDirectForCurrentLevel":0,"transactionPassword":"1234","emailVerified":false,"achievements":{"nationalTour":false,"internationalTour":false,"familyTour":false}},
  {"id":"user_1773052962503_87","userId":"5413397","email":"admin.bulk.1000001.1773052961477.87@auto.local","password":"user123","fullName":"Member 088","phone":"6250387698","country":"India","isActive":true,"isAdmin":false,"accountStatus":"active","blockedAt":null,"blockedUntil":null,"blockedReason":null,"createdAt":"2026-03-09T10:42:42.503Z","activatedAt":"2026-03-09T10:42:42.503Z","gracePeriodEnd":null,"sponsorId":"1000001","parentId":"3863373","position":"right","level":0,"directCount":0,"totalEarnings":0,"isCapped":false,"capLevel":0,"reEntryCount":0,"cycleCount":0,"requiredDirectForNextLevel":2,"completedDirectForCurrentLevel":0,"transactionPassword":"1234","emailVerified":false,"achievements":{"nationalTour":false,"internationalTour":false,"familyTour":false}},
  {"id":"user_1773052962504_88","userId":"3948360","email":"admin.bulk.1000001.1773052961477.88@auto.local","password":"user123","fullName":"Member 089","phone":"6250488979","country":"India","isActive":true,"isAdmin":false,"accountStatus":"active","blockedAt":null,"blockedUntil":null,"blockedReason":null,"createdAt":"2026-03-09T10:42:42.504Z","activatedAt":"2026-03-09T10:42:42.504Z","gracePeriodEnd":null,"sponsorId":"1000001","parentId":"8081104","position":"left","level":0,"directCount":0,"totalEarnings":0,"isCapped":false,"capLevel":0,"reEntryCount":0,"cycleCount":0,"requiredDirectForNextLevel":2,"completedDirectForCurrentLevel":0,"transactionPassword":"1234","emailVerified":false,"achievements":{"nationalTour":false,"internationalTour":false,"familyTour":false}},
  {"id":"user_1773052962505_89","userId":"8960213","email":"admin.bulk.1000001.1773052961477.89@auto.local","password":"user123","fullName":"Member 090","phone":"6250589555","country":"India","isActive":true,"isAdmin":false,"accountStatus":"active","blockedAt":null,"blockedUntil":null,"blockedReason":null,"createdAt":"2026-03-09T10:42:42.505Z","activatedAt":"2026-03-09T10:42:42.505Z","gracePeriodEnd":null,"sponsorId":"1000001","parentId":"8081104","position":"right","level":0,"directCount":0,"totalEarnings":0,"isCapped":false,"capLevel":0,"reEntryCount":0,"cycleCount":0,"requiredDirectForNextLevel":2,"completedDirectForCurrentLevel":0,"transactionPassword":"1234","emailVerified":false,"achievements":{"nationalTour":false,"internationalTour":false,"familyTour":false}},
  {"id":"user_1773052962726_90","userId":"3534599","email":"admin.bulk.1000001.1773052961477.90@auto.local","password":"user123","fullName":"Member 091","phone":"6272690135","country":"India","isActive":true,"isAdmin":false,"accountStatus":"active","blockedAt":null,"blockedUntil":null,"blockedReason":null,"createdAt":"2026-03-09T10:42:42.726Z","activatedAt":"2026-03-09T10:42:42.726Z","gracePeriodEnd":null,"sponsorId":"1000001","parentId":"8469337","position":"left","level":0,"directCount":0,"totalEarnings":0,"isCapped":false,"capLevel":0,"reEntryCount":0,"cycleCount":0,"requiredDirectForNextLevel":2,"completedDirectForCurrentLevel":0,"transactionPassword":"1234","emailVerified":false,"achievements":{"nationalTour":false,"internationalTour":false,"familyTour":false}},
  {"id":"user_1773052962727_91","userId":"8408792","email":"admin.bulk.1000001.1773052961477.91@auto.local","password":"user123","fullName":"Member 092","phone":"6272791829","country":"India","isActive":true,"isAdmin":false,"accountStatus":"active","blockedAt":null,"blockedUntil":null,"blockedReason":null,"createdAt":"2026-03-09T10:42:42.727Z","activatedAt":"2026-03-09T10:42:42.727Z","gracePeriodEnd":null,"sponsorId":"1000001","parentId":"8469337","position":"right","level":0,"directCount":0,"totalEarnings":0,"isCapped":false,"capLevel":0,"reEntryCount":0,"cycleCount":0,"requiredDirectForNextLevel":2,"completedDirectForCurrentLevel":0,"transactionPassword":"1234","emailVerified":false,"achievements":{"nationalTour":false,"internationalTour":false,"familyTour":false}},
  {"id":"user_1773052962730_92","userId":"8489404","email":"admin.bulk.1000001.1773052961477.92@auto.local","password":"user123","fullName":"Member 093","phone":"6273092836","country":"India","isActive":true,"isAdmin":false,"accountStatus":"active","blockedAt":null,"blockedUntil":null,"blockedReason":null,"createdAt":"2026-03-09T10:42:42.730Z","activatedAt":"2026-03-09T10:42:42.730Z","gracePeriodEnd":null,"sponsorId":"1000001","parentId":"7466908","position":"left","level":0,"directCount":0,"totalEarnings":0,"isCapped":false,"capLevel":0,"reEntryCount":0,"cycleCount":0,"requiredDirectForNextLevel":2,"completedDirectForCurrentLevel":0,"transactionPassword":"1234","emailVerified":false,"achievements":{"nationalTour":false,"internationalTour":false,"familyTour":false}},
  {"id":"user_1773052962732_93","userId":"5812648","email":"admin.bulk.1000001.1773052961477.93@auto.local","password":"user123","fullName":"Member 094","phone":"6273293671","country":"India","isActive":true,"isAdmin":false,"accountStatus":"active","blockedAt":null,"blockedUntil":null,"blockedReason":null,"createdAt":"2026-03-09T10:42:42.732Z","activatedAt":"2026-03-09T10:42:42.732Z","gracePeriodEnd":null,"sponsorId":"1000001","parentId":"7466908","position":"right","level":0,"directCount":0,"totalEarnings":0,"isCapped":false,"capLevel":0,"reEntryCount":0,"cycleCount":0,"requiredDirectForNextLevel":2,"completedDirectForCurrentLevel":0,"transactionPassword":"1234","emailVerified":false,"achievements":{"nationalTour":false,"internationalTour":false,"familyTour":false}},
  {"id":"user_1773052962734_94","userId":"9771001","email":"admin.bulk.1000001.1773052961477.94@auto.local","password":"user123","fullName":"Member 095","phone":"6273494894","country":"India","isActive":true,"isAdmin":false,"accountStatus":"active","blockedAt":null,"blockedUntil":null,"blockedReason":null,"createdAt":"2026-03-09T10:42:42.734Z","activatedAt":"2026-03-09T10:42:42.734Z","gracePeriodEnd":null,"sponsorId":"1000001","parentId":"6795355","position":"left","level":0,"directCount":0,"totalEarnings":0,"isCapped":false,"capLevel":0,"reEntryCount":0,"cycleCount":0,"requiredDirectForNextLevel":2,"completedDirectForCurrentLevel":0,"transactionPassword":"1234","emailVerified":false,"achievements":{"nationalTour":false,"internationalTour":false,"familyTour":false}},
  {"id":"user_1773052962736_95","userId":"4064967","email":"admin.bulk.1000001.1773052961477.95@auto.local","password":"user123","fullName":"Member 096","phone":"6273695902","country":"India","isActive":true,"isAdmin":false,"accountStatus":"active","blockedAt":null,"blockedUntil":null,"blockedReason":null,"createdAt":"2026-03-09T10:42:42.736Z","activatedAt":"2026-03-09T10:42:42.736Z","gracePeriodEnd":null,"sponsorId":"1000001","parentId":"6795355","position":"right","level":0,"directCount":0,"totalEarnings":0,"isCapped":false,"capLevel":0,"reEntryCount":0,"cycleCount":0,"requiredDirectForNextLevel":2,"completedDirectForCurrentLevel":0,"transactionPassword":"1234","emailVerified":false,"achievements":{"nationalTour":false,"internationalTour":false,"familyTour":false}},
  {"id":"user_1773052962741_96","userId":"8356256","email":"admin.bulk.1000001.1773052961477.96@auto.local","password":"user123","fullName":"Member 097","phone":"6274196576","country":"India","isActive":true,"isAdmin":false,"accountStatus":"active","blockedAt":null,"blockedUntil":null,"blockedReason":null,"createdAt":"2026-03-09T10:42:42.741Z","activatedAt":"2026-03-09T10:42:42.741Z","gracePeriodEnd":null,"sponsorId":"1000001","parentId":"4927255","position":"left","level":0,"directCount":0,"totalEarnings":0,"isCapped":false,"capLevel":0,"reEntryCount":0,"cycleCount":0,"requiredDirectForNextLevel":2,"completedDirectForCurrentLevel":0,"transactionPassword":"1234","emailVerified":false,"achievements":{"nationalTour":false,"internationalTour":false,"familyTour":false}},
  {"id":"user_1773052962743_97","userId":"7891382","email":"admin.bulk.1000001.1773052961477.97@auto.local","password":"user123","fullName":"Member 098","phone":"6274397796","country":"India","isActive":true,"isAdmin":false,"accountStatus":"active","blockedAt":null,"blockedUntil":null,"blockedReason":null,"createdAt":"2026-03-09T10:42:42.743Z","activatedAt":"2026-03-09T10:42:42.744Z","gracePeriodEnd":null,"sponsorId":"1000001","parentId":"4927255","position":"right","level":0,"directCount":0,"totalEarnings":0,"isCapped":false,"capLevel":0,"reEntryCount":0,"cycleCount":0,"requiredDirectForNextLevel":2,"completedDirectForCurrentLevel":0,"transactionPassword":"1234","emailVerified":false,"achievements":{"nationalTour":false,"internationalTour":false,"familyTour":false}},
  {"id":"user_1773052962747_98","userId":"2089292","email":"admin.bulk.1000001.1773052961477.98@auto.local","password":"user123","fullName":"Member 099","phone":"6274798101","country":"India","isActive":true,"isAdmin":false,"accountStatus":"active","blockedAt":null,"blockedUntil":null,"blockedReason":null,"createdAt":"2026-03-09T10:42:42.747Z","activatedAt":"2026-03-09T10:42:42.747Z","gracePeriodEnd":null,"sponsorId":"1000001","parentId":"3750316","position":"left","level":0,"directCount":0,"totalEarnings":0,"isCapped":false,"capLevel":0,"reEntryCount":0,"cycleCount":0,"requiredDirectForNextLevel":2,"completedDirectForCurrentLevel":0,"transactionPassword":"1234","emailVerified":false,"achievements":{"nationalTour":false,"internationalTour":false,"familyTour":false}},
  {"id":"user_1773052962749_99","userId":"3136021","email":"admin.bulk.1000001.1773052961477.99@auto.local","password":"user123","fullName":"Member 100","phone":"6274999794","country":"India","isActive":true,"isAdmin":false,"accountStatus":"active","blockedAt":null,"blockedUntil":null,"blockedReason":null,"createdAt":"2026-03-09T10:42:42.749Z","activatedAt":"2026-03-09T10:42:42.749Z","gracePeriodEnd":null,"sponsorId":"1000001","parentId":"3750316","position":"right","level":0,"directCount":0,"totalEarnings":0,"isCapped":false,"capLevel":0,"reEntryCount":0,"cycleCount":0,"requiredDirectForNextLevel":2,"completedDirectForCurrentLevel":0,"transactionPassword":"1234","emailVerified":false,"achievements":{"nationalTour":false,"internationalTour":false,"familyTour":false}},
  {"id":"user_1773052974485","userId":"1000001","email":"admin@matrixmlm.com","password":"admin123","fullName":"System Administrator","phone":"+1234567890","country":"USA","isActive":true,"isAdmin":true,"accountStatus":"active","blockedAt":null,"blockedUntil":null,"blockedReason":null,"createdAt":"2026-03-09T10:42:54.485Z","activatedAt":"2026-03-09T10:42:54.485Z","gracePeriodEnd":null,"sponsorId":null,"parentId":null,"position":null,"level":0,"directCount":0,"totalEarnings":0,"isCapped":false,"capLevel":0,"reEntryCount":0,"cycleCount":0,"requiredDirectForNextLevel":0,"completedDirectForCurrentLevel":0,"transactionPassword":"trans123","emailVerified":true,"achievements":{"nationalTour":false,"internationalTour":false,"familyTour":false}}
]
